msox3000/MSOX3000.py
msox3000/SCPI.py
msox3000/__init__.py
msox3000-0.4.0.dist-info/LICENSE
msox3000-0.4.0.dist-info/METADATA
msox3000-0.4.0.dist-info/WHEEL
msox3000-0.4.0.dist-info/top_level.txt
msox3000-0.4.0.dist-info/RECORD
