Metadata-Version: 2.1
Name: msox3000
Version: 0.4.0
Summary: Control of HP/Agilent/Keysight MSO-X/DSO-X 3000A Oscilloscope through python via PyVisa
Home-page: https://github.com/sgoadhouse/msox3000
Author: Stephen Goadhouse
Author-email: sgoadhouse@virginia.edu
Maintainer: Stephen Goadhouse
Maintainer-email: sgoadhouse@virginia.edu
License: MIT
Keywords: HP,Agilent,Keysight,MSO3000,MSOX3000,DSO3000,DSOX3000PyVISA,VISA,SCPI,INSTRUMENT
Platform: UNKNOWN
Classifier: Development Status :: 4 - Beta
Classifier: Intended Audience :: Developers
Classifier: Intended Audience :: Education
Classifier: Intended Audience :: Science/Research
Classifier: License :: OSI Approved :: MIT License
Classifier: Programming Language :: Python
Classifier: Topic :: Scientific/Engineering
Classifier: Topic :: Scientific/Engineering :: Physics
Classifier: Topic :: Software Development
Classifier: Topic :: Software Development :: Libraries
Classifier: Topic :: Software Development :: Libraries :: Python Modules
Requires-Python: >=3.6
Requires-Dist: pyvisa (>=1.11.3)
Requires-Dist: pyvisa-py (>=0.5.1)
Requires-Dist: argparse
Requires-Dist: QuantiPhy (>=2.3.0)
